Workbook

Sheet README
A1: Pricing Tier Comparison Model — V1 Entry Ladder
A3: Author | B3: Yoshi + Claude (S87 close)
A4: Date | B4: 2026-05-19
A5: Question | B5: V1 entry ladder: $1.99/$4.99 (Scenario A) vs $4.99/$9.99 (Scenario B). Which yields more Year-1 revenue?
A6: Companion doc | B6: ~/Desktop/App/PRICING_TIER_ANALYSIS.md
A8: How to use this model
A9: 1. Inputs tab — change blue cells to test different assumptions. All formulas downstream update.
A10: 2. ScenarioA tab — $1.99 / $4.99 ladder, calculations across three volume scenarios.
A11: 3. ScenarioB tab — $4.99 / $9.99 ladder, calculations across three volume scenarios.
A12: 4. Comparison tab — side-by-side Year-1 net revenue for both ladders.
A13: 5. Sensitivity tab — breakeven analysis: at what free-to-paid conversion ratio does Scenario B win?
A15: Color coding
A16: Blue text = hardcoded input you can change
A17: Black text = formula, do not edit directly
A18: Green text = links to other sheets
A19: Yellow background = key sensitivity input
A20: Orange background = key output / decision driver

Sheet Inputs
A1: INPUTS — All assumptions, change blue cells to test
A3: Year-1 install volume scenarios
A4: Scenario | B4: Total Y1 installs | C4: Rationale
A5: Conservative | B5: 10000 | C5: Cold launch, no audience, organic discovery only
A6: Base | B6: 30000 | C6: Modest YouTube cross-channel funnel + organic Bible-app search
A7: Optimistic | B7: 75000 | C7: Share/watermark viral loop + restored-names community word-of-mouth
A9: Scenario A — $1.99 / $4.99 entry ladder
A10: Free → $1.99 conversion rate | B10: Conservative | C10: Base | D10: Optimistic
A11: Free → $1.99 rate | B11: 0.04 | C11: 0.07 | D11: 0.1
A12: $1.99 → $4.99 upgrade rate (within 6 mo) | B12: 0.22 | C12: 0.22 | D12: 0.22
A14: Scenario B — $4.99 / $9.99 entry ladder
A15: Free → $4.99 conversion rate | B15: Conservative | C15: Base | D15: Optimistic
A16: Free → $4.99 rate | B16: 0.022 | C16: 0.035 | D16: 0.05
A17: $4.99 → $9.99 upgrade rate (within 6 mo) | B17: 0.18 | C17: 0.18 | D17: 0.18
A19: Pricing
A20: Tier | B20: Monthly price
A21: $1.99 tier | B21: 1.99
A22: $4.99 tier | B22: 4.99
A23: $9.99 tier | B23: 9.99
A25: Annual churn rates
A26: Tier | B26: Annual churn | C26: Source / reasoning
A27: $1.99 churn | B27: 0.35 | C27: Low-price tier, less commitment, higher churn
A28: $4.99 churn | B28: 0.25 | C28: Mid-price, more committed users
A29: $9.99 churn | B29: 0.18 | C29: Premium-price, filtered for committed users
A31: Cost factors
A32: Stripe + ops cost factor | B32: 0.06 | C32: Stripe 2.9% + 30c/txn + accounting overhead
A33: Refund/chargeback rate at sub-$5 tiers | B33: 0.01 | C33: Industry standard ~1% at low-price tiers
A34: Refund/chargeback rate at $5+ tiers | B34: 0.035 | C34: Industry standard 2-4% at higher prices
A36: Second-order corrections (Scenario B drags)
A37: Install volume drop under higher pricing | B37: 0.15 | C37: Word-of-mouth velocity slower at high prices; fewer reviews
A38: Mid-year churn factor (half-year average) | B38: 0.5 | C38: Churn applies progressively, not all at end of year

Sheet ScenarioA
A1: Scenario A — $1.99 / $4.99 entry ladder
A2: Year-1 revenue calculation, three install volumes
A4: Metric | B4: Conservative | C4: Base | D4: Optimistic | E4: Formula
A5: Y1 installs | B5: =Inputs!B5 -> 10000 | C5: =Inputs!B6 -> 30000 | D5: =Inputs!B7 -> 75000 | E5: From Inputs
A6: Free → $1.99 conversion rate | B6: =Inputs!B11 -> 0.04 | C6: =Inputs!C11 -> 0.07 | D6: =Inputs!D11 -> 0.1 | E6: From Inputs
A7: Users entering at $1.99 | B7: =B5*B6 -> 400 | C7: =C5*C6 -> 2100 | D7: =D5*D6 -> 7500 | E7: installs × conversion rate
A8: $1.99 → $4.99 upgrade rate (6 mo) | B8: =Inputs!B12 -> 0.22 | C8: =Inputs!C12 -> 0.22 | D8: =Inputs!D12 -> 0.22 | E8: From Inputs
A9: Users upgraded to $4.99 by month 6 | B9: =B7*B8 -> 88 | C9: =C7*C8 -> 462 | D9: =D7*D8 -> 1650 | E9: $1.99 users × upgrade rate
A10: Users still at $1.99 by month 6 | B10: =B7-B9 -> 312 | C10: =C7-C9 -> 1638 | D10: =D7-D9 -> 5850 | E10: $1.99 users − upgraded
A12: Revenue first 6 months (all at $1.99) | B12: =B7*Inputs!$B$21*6 -> 4776 | C12: =C7*Inputs!$B$21*6 -> 25074 | D12: =D7*Inputs!$B$21*6 -> 89550 | E12: $1.99 users × $1.99 × 6 months
A13: Revenue second 6 months ($1.99 stayers) | B13: =B10*Inputs!$B$21*6 -> 3725.28 | C13: =C10*Inputs!$B$21*6 -> 19557.72 | D13: =D10*Inputs!$B$21*6 -> 69849 | E13: remaining $1.99 × $1.99 × 6
A14: Revenue second 6 months ($4.99 upgraded) | B14: =B9*Inputs!$B$22*6 -> 2634.72 | C14: =C9*Inputs!$B$22*6 -> 13832.28 | D14: =D9*Inputs!$B$22*6 -> 49401 | E14: upgraded users × $4.99 × 6
A15: Subtotal — gross revenue pre-churn | B15: =SUM(B12:B14) -> 11136 | C15: =SUM(C12:C14) -> 58464 | D15: =SUM(D12:D14) -> 208800
A17: Blended churn factor (mid-year average) | B17: =((1-((B10*Inputs!$B$27+B9*Inputs!$B$28)/(B10+B9))*Inputs!$B$38)) -> 0.836 | C17: =((1-((C10*Inputs!$B$27+C9*Inputs!$B$28)/(C10+C9))*Inputs!$B$38)) -> 0.836 | D17: =((1-((D10*Inputs!$B$27+D9*Inputs!$B$28)/(D10+D9))*Inputs!$B$38)) -> 0.836 | E17: 1 − (weighted blended churn × half-year factor)
A18: Revenue after churn | B18: =B15*B17 -> 9309.696 | C18: =C15*C17 -> 48875.904 | D18: =D15*D17 -> 174556.8
A19: Refund/chargeback rate (blended) | B19: =((B10*Inputs!$B$33+B9*Inputs!$B$34)/(B10+B9)) -> 0.0155 | C19: =((C10*Inputs!$B$33+C9*Inputs!$B$34)/(C10+C9)) -> 0.0155 | D19: =((D10*Inputs!$B$33+D9*Inputs!$B$34)/(D10+D9)) -> 0.0155 | E19: Weighted by user count
A20: Revenue after refunds | B20: =B18*(1-B19) -> 9165.3957 | C20: =C18*(1-C19) -> 48118.327 | D20: =D18*(1-D19) -> 171851.17
A21: After Stripe/ops cost | B21: =B20*(1-Inputs!$B$32) -> 8615.472 | C21: =C20*(1-Inputs!$B$32) -> 45231.228 | D21: =D20*(1-Inputs!$B$32) -> 161540.1
A23: NET Y1 REVENUE — SCENARIO A | B23: =B21 -> 8615.472 | C23: =C21 -> 45231.228 | D23: =D21 -> 161540.1

Sheet ScenarioB
A1: Scenario B — $4.99 / $9.99 entry ladder
A2: Year-1 revenue calculation, three install volumes
A4: Metric | B4: Conservative | C4: Base | D4: Optimistic | E4: Formula
A5: Y1 installs (raw) | B5: =Inputs!B5 -> 10000 | C5: =Inputs!B6 -> 30000 | D5: =Inputs!B7 -> 75000 | E5: From Inputs
A6: Install drop factor (higher prices) | B6: =Inputs!$B$37 -> 0.15 | C6: =Inputs!$B$37 -> 0.15 | D6: =Inputs!$B$37 -> 0.15
A7: Effective installs after drop | B7: =B5*(1-B6) -> 8500 | C7: =C5*(1-C6) -> 25500 | D7: =D5*(1-D6) -> 63750 | E7: raw installs × (1 − drop)
A8: Free → $4.99 conversion rate | B8: =Inputs!B16 -> 0.022 | C8: =Inputs!C16 -> 0.035 | D8: =Inputs!D16 -> 0.05 | E8: From Inputs
A9: Users entering at $4.99 | B9: =B7*B8 -> 187 | C9: =C7*C8 -> 892.5 | D9: =D7*D8 -> 3187.5 | E9: effective installs × conv rate
A10: $4.99 → $9.99 upgrade rate (6 mo) | B10: =Inputs!B17 -> 0.18 | C10: =Inputs!C17 -> 0.18 | D10: =Inputs!D17 -> 0.18 | E10: From Inputs
A11: Users upgraded to $9.99 by month 6 | B11: =B9*B10 -> 33.66 | C11: =C9*C10 -> 160.65 | D11: =D9*D10 -> 573.75 | E11: $4.99 users × upgrade rate
A12: Users still at $4.99 by month 6 | B12: =B9-B11 -> 153.34 | C12: =C9-C11 -> 731.85 | D12: =D9-D11 -> 2613.75 | E12: $4.99 users − upgraded
A14: Revenue first 6 months (all at $4.99) | B14: =B9*Inputs!$B$22*6 -> 5598.78 | C14: =C9*Inputs!$B$22*6 -> 26721.45 | D14: =D9*Inputs!$B$22*6 -> 95433.75
A15: Revenue second 6 months ($4.99 stayers) | B15: =B12*Inputs!$B$22*6 -> 4590.9996 | C15: =C12*Inputs!$B$22*6 -> 21911.589 | D15: =D12*Inputs!$B$22*6 -> 78255.675
A16: Revenue second 6 months ($9.99 upgraded) | B16: =B11*Inputs!$B$23*6 -> 2017.5804 | C16: =C11*Inputs!$B$23*6 -> 9629.361 | D16: =D11*Inputs!$B$23*6 -> 34390.575
A17: Subtotal — gross revenue pre-churn | B17: =SUM(B14:B16) -> 12207.36 | C17: =SUM(C14:C16) -> 58262.4 | D17: =SUM(D14:D16) -> 208080
A19: Blended churn factor (mid-year average) | B19: =(1-((B12*Inputs!$B$28+B11*Inputs!$B$29)/(B12+B11))*Inputs!$B$38) -> 0.8813 | C19: =(1-((C12*Inputs!$B$28+C11*Inputs!$B$29)/(C12+C11))*Inputs!$B$38) -> 0.8813 | D19: =(1-((D12*Inputs!$B$28+D11*Inputs!$B$29)/(D12+D11))*Inputs!$B$38) -> 0.8813
A20: Revenue after churn | B20: =B17*B19 -> 10758.346 | C20: =C17*C19 -> 51346.653 | D20: =D17*D19 -> 183380.9
A21: Refund/chargeback rate ($5+ tiers) | B21: =Inputs!$B$34 -> 0.035 | C21: =Inputs!$B$34 -> 0.035 | D21: =Inputs!$B$34 -> 0.035
A22: Revenue after refunds | B22: =B20*(1-B21) -> 10381.804 | C22: =C20*(1-C21) -> 49549.52 | D22: =D20*(1-D21) -> 176962.57
A23: After Stripe/ops cost | B23: =B22*(1-Inputs!$B$32) -> 9758.896 | C23: =C22*(1-Inputs!$B$32) -> 46576.549 | D23: =D22*(1-Inputs!$B$32) -> 166344.82
A25: NET Y1 REVENUE — SCENARIO B | B25: =B23 -> 9758.896 | C25: =C23 -> 46576.549 | D25: =D23 -> 166344.82

Sheet Comparison
A1: Comparison — Scenario A vs Scenario B
A3: Net Year-1 revenue by scenario
A4: Scenario | B4: Conservative (10K) | C4: Base (30K) | D4: Optimistic (75K)
A5: Scenario A ($1.99 / $4.99) | B5: =ScenarioA!B23 -> 8615.472 | C5: =ScenarioA!C23 -> 45231.228 | D5: =ScenarioA!D23 -> 161540.1
A6: Scenario B ($4.99 / $9.99) | B6: =ScenarioB!B25 -> 9758.896 | C6: =ScenarioB!C25 -> 46576.549 | D6: =ScenarioB!D25 -> 166344.82
A7: Delta (B minus A) | B7: =B6-B5 -> 1143.424 | C7: =C6-C5 -> 1345.3212 | D7: =D6-D5 -> 4804.7186
A8: % difference (B vs A) | B8: =(B6-B5)/B5 -> 0.13271751 | C8: =(C6-C5)/C5 -> 0.029743194 | D8: =(D6-D5)/D5 -> 0.029743194
A9: Winner | B9: =IF(B5>B6,"Scenario A",IF(B6>B5,"Scenario B","Tie")) -> Scenario B | C9: =IF(C5>C6,"Scenario A",IF(C6>C5,"Scenario B","Tie")) -> Scenario B | D9: =IF(D5>D6,"Scenario A",IF(D6>D5,"Scenario B","Tie")) -> Scenario B
A11: Paying user count (drives reviews, viral, Y2 funnel)
A12: Metric | B12: Conservative | C12: Base | D12: Optimistic
A13: Scenario A — total paying users | B13: =ScenarioA!B7 -> 400 | C13: =ScenarioA!C7 -> 2100 | D13: =ScenarioA!D7 -> 7500
A14: Scenario B — total paying users | B14: =ScenarioB!B9 -> 187 | C14: =ScenarioB!C9 -> 892.5 | D14: =ScenarioB!D9 -> 3187.5
A15: Delta paying users (A advantage) | B15: =B13-B14 -> 213 | C15: =C13-C14 -> 1207.5 | D15: =D13-D14 -> 4312.5
A17: Strategic factors (not in dollar terms — must weight separately)
A18: Factor | B18: Favors | C18: Rationale
A19: Larger paying base → faster review accumulation | B19: Scenario A | C19: Year-1 App Store ranking + word-of-mouth
A20: Easier to raise prices later than cut later | B20: Scenario A | C20: Asymmetric risk; price changes harder downward
A21: Stronger Y2 cascade into $9.99 / $14.99 | B21: Scenario A | C21: $1.99 user base feeds Y2 funnel
A22: Mission alignment (framework accessibility) | B22: Scenario A | C22: Voice skill posture — patience toward deceived
A23: Filters for committed users with higher LTV | B23: Scenario B | C23: Premium pricing acts as quality signal
A24: Higher per-user revenue | B24: Scenario B | C24: Each subscriber more lucrative
A25: Better retention (Day-35 retention 2x) | B25: Scenario B | C25: Adapty 2025 data — high prices retain better
A26: Faster cash generation in Y1 (per converter) | B26: Scenario B | C26: Each conversion more cash up front

Sheet Sensitivity
A1: Sensitivity — Breakeven analysis at Base install volume (30K)
A3: This table shows: at the base install volume (30K), how does the net revenue gap change as we vary the Free → $4.99 conversion rate? Scenario A's $1.99 conversion rate is held at the base value (7%).
A5: Free → $4.99 conv rate | B5: 0.02 | C5: 0.025 | D5: 0.03 | E5: 0.035 | F5: 0.04 | G5: 0.045
A7: Scenario A net Y1 revenue (Base, 30K) | B7: =ScenarioA!C23 -> 45231.228
A8: Scenario B net Y1 revenue at this conv rate | B8: =(Inputs!$B$6*(1-Inputs!$B$37)*B5*Inputs!$B$22*6 + Inputs!$B$6*(1-Inputs!$B$37)*B5*(1-Inputs!$C$17)*Inputs!$B$22*6 + Inputs!$B$6*(1-Inputs!$B$37)*B5*Inputs!$C$17*Inputs!$B$23*6)*(1-Inputs!$B$34)*(1-Inputs!$B$32)*(1-(((1-Inputs!$C$17)*Inputs!$B$28+Inputs!$C$17*Inputs!$B$29))*Inputs!$B$38) -> 26615.171 | C8: =(Inputs!$B$6*(1-Inputs!$B$37)*C5*Inputs!$B$22*6 + Inputs!$B$6*(1-Inputs!$B$37)*C5*(1-Inputs!$C$17)*Inputs!$B$22*6 + Inputs!$B$6*(1-Inputs!$B$37)*C5*Inputs!$C$17*Inputs!$B$23*6)*(1-Inputs!$B$34)*(1-Inputs!$B$32)*(1-(((1-Inputs!$C$17)*Inputs!$B$28+Inputs!$C$17*Inputs!$B$29))*Inputs!$B$38) -> 33268.964 | D8: =(Inputs!$B$6*(1-Inputs!$B$37)*D5*Inputs!$B$22*6 + Inputs!$B$6*(1-Inputs!$B$37)*D5*(1-Inputs!$C$17)*Inputs!$B$22*6 + Inputs!$B$6*(1-Inputs!$B$37)*D5*Inputs!$C$17*Inputs!$B$23*6)*(1-Inputs!$B$34)*(1-Inputs!$B$32)*(1-(((1-Inputs!$C$17)*Inputs!$B$28+Inputs!$C$17*Inputs!$B$29))*Inputs!$B$38) -> 39922.756 | E8: =(Inputs!$B$6*(1-Inputs!$B$37)*E5*Inputs!$B$22*6 + Inputs!$B$6*(1-Inputs!$B$37)*E5*(1-Inputs!$C$17)*Inputs!$B$22*6 + Inputs!$B$6*(1-Inputs!$B$37)*E5*Inputs!$C$17*Inputs!$B$23*6)*(1-Inputs!$B$34)*(1-Inputs!$B$32)*(1-(((1-Inputs!$C$17)*Inputs!$B$28+Inputs!$C$17*Inputs!$B$29))*Inputs!$B$38) -> 46576.549 | F8: =(Inputs!$B$6*(1-Inputs!$B$37)*F5*Inputs!$B$22*6 + Inputs!$B$6*(1-Inputs!$B$37)*F5*(1-Inputs!$C$17)*Inputs!$B$22*6 + Inputs!$B$6*(1-Inputs!$B$37)*F5*Inputs!$C$17*Inputs!$B$23*6)*(1-Inputs!$B$34)*(1-Inputs!$B$32)*(1-(((1-Inputs!$C$17)*Inputs!$B$28+Inputs!$C$17*Inputs!$B$29))*Inputs!$B$38) -> 53230.342 | G8: =(Inputs!$B$6*(1-Inputs!$B$37)*G5*Inputs!$B$22*6 + Inputs!$B$6*(1-Inputs!$B$37)*G5*(1-Inputs!$C$17)*Inputs!$B$22*6 + Inputs!$B$6*(1-Inputs!$B$37)*G5*Inputs!$C$17*Inputs!$B$23*6)*(1-Inputs!$B$34)*(1-Inputs!$B$32)*(1-(((1-Inputs!$C$17)*Inputs!$B$28+Inputs!$C$17*Inputs!$B$29))*Inputs!$B$38) -> 59884.134
A9: Delta (B minus A) | B9: =B8-$B$7 -> -18616.057 | C9: =C8-$B$7 -> -11962.264 | D9: =D8-$B$7 -> -5308.4715 | E9: =E8-$B$7 -> 1345.3212 | F9: =F8-$B$7 -> 7999.1139 | G9: =G8-$B$7 -> 14652.907
A10: Winner at this rate | B10: =IF(B8>$B$7,"Scenario B","Scenario A") -> Scenario A | C10: =IF(C8>$B$7,"Scenario B","Scenario A") -> Scenario A | D10: =IF(D8>$B$7,"Scenario B","Scenario A") -> Scenario A | E10: =IF(E8>$B$7,"Scenario B","Scenario A") -> Scenario B | F10: =IF(F8>$B$7,"Scenario B","Scenario A") -> Scenario B | G10: =IF(G8>$B$7,"Scenario B","Scenario A") -> Scenario B
A12: Interpretation
A13: The Free → $4.99 conversion rate is the swing variable. Industry benchmarks (RevenueCat 2025) suggest a 53% drop from low-tier to mid-tier conversion. If $1.99 conversion is 7%, $4.99 conversion would be roughly 3.3%.
A14: The breakeven point is where Scenario B revenue = Scenario A revenue. Above the breakeven $4.99 conversion rate, Scenario B wins. Below it, Scenario A wins.
A15: Note: This sensitivity holds all OTHER variables constant. To test other levers, change values on the Inputs tab and rerun.
